[{"model": "clinic.clinic", "pk": 1, "fields": {"logo": "Atlas_Logo_OG_dFsf9G4.png", "name": "HSR", "tagline": "FEEL better, but als", "address_line_1": "Ground Floor, 680, 13th Cross Rd", "address_line_2": "1st Sector, HSR Layout", "city": "Bengaluru", "state": "Karnataka", "country": "India", "pincode": 560102, "email": "hsrlayout@atlaschiroindia.com", "phone_no_1": 919606270303, "phone_no_2": null, "website": "https://www.atlaschiroindia.com/", "slot_duration": "15", "status": true, "created_by": 1, "updated_by": 1, "created_at": "2023-06-03T16:12:02.927Z", "updated_at": "2023-06-03T16:37:57.730Z"}}, {"model": "clinic.clinic", "pk": 2, "fields": {"logo": "Atlas_Logo_OG.png", "name": "Whitefield", "tagline": "Heal Better Feel Better", "address_line_1": "301, 3rd Floor, Arcade @, Brigade Metropolis, Garudachar Palya, Mahadevapura", "address_line_2": "", "city": "Bengaluru", "state": "Karnataka", "country": "India", "pincode": 560048, "email": "whitefield@atlaschiroindia.com", "phone_no_1": 9606704304, "phone_no_2": null, "website": "https://www.atlaschiroindia.com/", "slot_duration": "15", "status": true, "created_by": 3, "updated_by": 3, "created_at": "2023-06-03T16:34:37.319Z", "updated_at": "2023-06-03T16:34:37.319Z"}}, {"model": "clinic.clinic", "pk": 3, "fields": {"logo": "Atlas_Logo_OG_8pYayB8.png", "name": "Indira Nagar", "tagline": "Heal Better Feel Better", "address_line_1": "1st Floor, Kannambilles Building, #820, 10th A Main Rd, Hoysala Nagar, Indiranagar", "address_line_2": "", "city": "Bengaluru", "state": "Karnataka", "country": "India", "pincode": 560038, "email": "indiranagar@atlaschiroindia.com", "phone_no_1": 9606270202, "phone_no_2": null, "website": "https://www.atlaschiroindia.com/", "slot_duration": "15", "status": true, "created_by": 3, "updated_by": 3, "created_at": "2023-06-03T16:37:32.553Z", "updated_at": "2023-06-03T16:37:32.554Z"}}, {"model": "clinic.clinic", "pk": 4, "fields": {"logo": "", "name": "Chennai", "tagline": "Heal Better Feel Better", "address_line_1": "#6, 2nd floor, Rajakrishnan St, Teynampet", "address_line_2": "", "city": "Chennai", "state": "Tamil Nadu", "country": "India", "pincode": 600018, "email": "chennai@atlaschiroindia.com", "phone_no_1": 9740416004, "phone_no_2": null, "website": "www.atlaschiroindia.com", "slot_duration": "15", "status": true, "created_by": 3, "updated_by": 3, "created_at": "2023-06-03T16:40:08.421Z", "updated_at": "2023-06-03T16:40:08.421Z"}}, {"model": "clinic.clinic", "pk": 5, "fields": {"logo": "", "name": "Hyderabad", "tagline": "Heal Better Feel Better", "address_line_1": "Ashoka Capital, Unit 405, Road no.2, Opp.KBR Park, Banjara Hills", "address_line_2": "", "city": "Hyderabad", "state": "Telangana", "country": "India", "pincode": 500034, "email": "hyderabad@atlaschiroindia.com", "phone_no_1": 7286958197, "phone_no_2": null, "website": "www.atlaschiroindia.com", "slot_duration": "15", "status": true, "created_by": 3, "updated_by": 3, "created_at": "2023-06-03T16:42:08.442Z", "updated_at": "2023-06-03T16:42:08.442Z"}}]